worldsim.py
worldsim-0.0.0.dist-info/METADATA
worldsim-0.0.0.dist-info/WHEEL
worldsim-0.0.0.dist-info/RECORD
